chromedriver_autoinstall/__init__.py
chromedriver_autoinstall/command_line.py
chromedriver_autoinstall/script.py
chromedriver_autoinstall-0.0.9.dist-info/LICENSE
chromedriver_autoinstall-0.0.9.dist-info/METADATA
chromedriver_autoinstall-0.0.9.dist-info/WHEEL
chromedriver_autoinstall-0.0.9.dist-info/entry_points.txt
chromedriver_autoinstall-0.0.9.dist-info/top_level.txt
chromedriver_autoinstall-0.0.9.dist-info/RECORD
