Metadata-Version: 2.1
Name: chromedriver-autoinstall
Version: 0.0.9
Summary: Script to automatically install the ChromeDriver release compatible with the client's Chrome version. Supports all versions of Chrome.
Home-page: https://github.com/RoastSea8/chromedriver_autoinstall
Author: RoastSea8 (Aditya Tomar)
Author-email: aditya26042005@gmail.com
License: MIT
Keywords: chromedriver,install,automation,autoinstall,autoinstaller,autoinstallscript,selenium
Classifier: Development Status :: 4 - Beta
Classifier: Topic :: Software Development :: Testing
Classifier: Topic :: System :: Installation/Setup
Classifier: Topic :: Software Development :: Libraries :: Python Modules
Classifier: License :: OSI Approved :: MIT License
Classifier: Programming Language :: Python :: 3
Classifier: Programming Language :: Python :: 3.6
Classifier: Programming Language :: Python :: 3.7
Classifier: Programming Language :: Python :: 3.8
Classifier: Programming Language :: Python :: 3.9
Classifier: Programming Language :: Python :: 3.10
Classifier: Operating System :: MacOS :: MacOS X
Classifier: Operating System :: Microsoft :: Windows
Requires-Python: >=3.6
License-File: LICENSE
Requires-Dist: requests
Requires-Dist: bs4
Requires-Dist: lxml
